XinzhaiLiaoyuGuanyuanchen/Dockerfile
XinzhaiLiaoyuGuanyuanchen/README.md
XinzhaiLiaoyuGuanyuanchen/__init__.py
XinzhaiLiaoyuGuanyuanchen/__main__.py
XinzhaiLiaoyuGuanyuanchen/file.epub
XinzhaiLiaoyuGuanyuanchen/index.html
XinzhaiLiaoyuGuanyuanchen/css/__init__.py
XinzhaiLiaoyuGuanyuanchen/css/annotations.css
XinzhaiLiaoyuGuanyuanchen/css/main.css
XinzhaiLiaoyuGuanyuanchen/css/normalize.css
XinzhaiLiaoyuGuanyuanchen/css/popup.css
XinzhaiLiaoyuGuanyuanchen/font/__init__.py
XinzhaiLiaoyuGuanyuanchen/font/fontello.eot
XinzhaiLiaoyuGuanyuanchen/font/fontello.svg
XinzhaiLiaoyuGuanyuanchen/font/fontello.ttf
XinzhaiLiaoyuGuanyuanchen/font/fontello.woff
XinzhaiLiaoyuGuanyuanchen/img/__init__.py
XinzhaiLiaoyuGuanyuanchen/img/annotator-glyph-sprite.png
XinzhaiLiaoyuGuanyuanchen/img/annotator-icon-sprite.png
XinzhaiLiaoyuGuanyuanchen/img/apple-touch-icon.png
XinzhaiLiaoyuGuanyuanchen/img/cancelfullscreen.png
XinzhaiLiaoyuGuanyuanchen/img/close.png
XinzhaiLiaoyuGuanyuanchen/img/fullscreen.png
XinzhaiLiaoyuGuanyuanchen/img/loader.gif
XinzhaiLiaoyuGuanyuanchen/img/menu-icon.png
XinzhaiLiaoyuGuanyuanchen/img/save.png
XinzhaiLiaoyuGuanyuanchen/img/saved.png
XinzhaiLiaoyuGuanyuanchen/img/settings-s.png
XinzhaiLiaoyuGuanyuanchen/img/settings.png
XinzhaiLiaoyuGuanyuanchen/img/star.png
XinzhaiLiaoyuGuanyuanchen/js/__init__.py
XinzhaiLiaoyuGuanyuanchen/js/epub.js
XinzhaiLiaoyuGuanyuanchen/js/epub.min.js
XinzhaiLiaoyuGuanyuanchen/js/epub.min.map
XinzhaiLiaoyuGuanyuanchen/js/hooks.min.js
XinzhaiLiaoyuGuanyuanchen/js/hooks.min.map
XinzhaiLiaoyuGuanyuanchen/js/reader.js
XinzhaiLiaoyuGuanyuanchen/js/reader.js.map
XinzhaiLiaoyuGuanyuanchen/js/reader.min.js
XinzhaiLiaoyuGuanyuanchen/js/reader.min.map
XinzhaiLiaoyuGuanyuanchen/js/hooks/__init__.py
XinzhaiLiaoyuGuanyuanchen/js/hooks/extensions/__init__.py
XinzhaiLiaoyuGuanyuanchen/js/hooks/extensions/highlight.js
XinzhaiLiaoyuGuanyuanchen/js/libs/__init__.py
XinzhaiLiaoyuGuanyuanchen/js/libs/jquery.min.js
xinzhai_liaoyu_guanyuanchen-2022.10.3.0.dist-info/METADATA
xinzhai_liaoyu_guanyuanchen-2022.10.3.0.dist-info/WHEEL
xinzhai_liaoyu_guanyuanchen-2022.10.3.0.dist-info/entry_points.txt
xinzhai_liaoyu_guanyuanchen-2022.10.3.0.dist-info/top_level.txt
xinzhai_liaoyu_guanyuanchen-2022.10.3.0.dist-info/RECORD
